[
  {
    "id": "eow1g58wkzbwd4zac7fbq4vg",
    "to": {
      "groupId": "iswxdhwrgmz4ugvbghbrjary"
    },
    "from": {
      "blockId": "ncbz7diraoaf5gw5mckpy6d5"
    }
  },
  {
    "id": "zzo45covz7dbc2xij522gsb8",
    "to": {
      "blockId": "hm9zem1r0m2fuii2h8t6dkfb",
      "groupId": "xyxmeuk9o4i75374vn4jenio"
    },
    "from": {
      "blockId": "mi2mfnjxofi772gnzlqycic1"
    }
  },
  {
    "id": "z0f4rz839dtnhj9by4yc1xl2",
    "to": {
      "groupId": "jndjpbk845u64o1c311x6o5b"
    },
    "from": {
      "itemId": "idnhzowx2p8hp6yuqgpeg5cz",
      "blockId": "mi2mfnjxofi772gnzlqycic1"
    }
  },
  {
    "id": "f5pzibv6dtzffcs19o9aun6s",
    "to": {
      "groupId": "ki3cih7a5vdpiz2rjkia9j97"
    },
    "from": {
      "blockId": "yxqwy626m009ltxcl87zjywb"
    }
  },
  {
    "id": "oxs3ei9y2c3lvkkqkxa3dgta",
    "to": {
      "groupId": "ki3cih7a5vdpiz2rjkia9j97"
    },
    "from": {
      "blockId": "hm9zem1r0m2fuii2h8t6dkfb"
    }
  },
  {
    "id": "jd19nr5kp9dn7s9i710hqg75",
    "to": {
      "blockId": "iohgbduct453ah9as6ujubpb",
      "groupId": "jqg17imoy5gxe2a23grnp17h"
    },
    "from": {
      "blockId": "ni17i15qotyt36wly0a8ty7f"
    }
  },
  {
    "id": "yviyv1gvkvuouy936pf5fzu6",
    "to": {
      "groupId": "iswxdhwrgmz4ugvbghbrjary"
    },
    "from": {
      "blockId": "iohgbduct453ah9as6ujubpb"
    }
  }
]